replyapp
